LICENSE
README.md
requirements.txt
setup.py
dummy_0532.egg-info/PKG-INFO
dummy_0532.egg-info/SOURCES.txt
dummy_0532.egg-info/dependency_links.txt
dummy_0532.egg-info/not-zip-safe
dummy_0532.egg-info/requires.txt
dummy_0532.egg-info/top_level.txt
up42/__init__.py
up42/_version.txt
up42/asset.py
up42/auth.py
up42/catalog.py
up42/estimation.py
up42/job.py
up42/jobcollection.py
up42/jobtask.py
up42/order.py
up42/project.py
up42/storage.py
up42/tools.py
up42/utils.py
up42/viztools.py
up42/workflow.py
up42/data/aoi_berlin.geojson
up42/data/aoi_washington.geojson