Metadata-Version: 2.1
Name: dummy-0532
Version: 0.3.5
Summary: Dummy package for test
Home-page: https://github.com/andher1802/dummy_0532.git
Author: UP42
Author-email: andres.hernandez-camacho@up42.com
License: MIT
Platform: UNKNOWN
Classifier: Programming Language :: Python :: 3
Classifier: License :: OSI Approved :: MIT License
Classifier: Operating System :: OS Independent
Classifier: Development Status :: 4 - Beta
Classifier: Intended Audience :: Developers
Requires-Python: >=3.7, <=3.10
License-File: LICENSE
